socos/__init__.py
socos/core.py
socos/exceptions.py
socos/mixer.py
socos/music_lib.py
socos/runner.py
socos/utils.py
socos-0.2.dist-info/DESCRIPTION.rst
socos-0.2.dist-info/METADATA
socos-0.2.dist-info/RECORD
socos-0.2.dist-info/WHEEL
socos-0.2.dist-info/entry_points.txt
socos-0.2.dist-info/metadata.json
socos-0.2.dist-info/top_level.txt
