Metadata-Version: 2.0
Name: socos
Version: 0.2
Summary: socos is a commandline tool for controlling Sonos speakers
Home-page: https://github.com/SoCo/socos
Author: SoCo team
Author-email: python-soco@googlegroups.com
License: MIT License
Platform: UNKNOWN
Requires-Dist: soco (==0.11.1)
